fwsimple/__init__.py
fwsimple/constants.py
fwsimple/firewall.py
fwsimple/lib.py
fwsimple/xtypes.py
fwsimple/zone.py
fwsimple/engines/__init__.py
fwsimple/engines/iptables.py
fwsimple/rules/__init__.py
fwsimple/rules/filter.py
fwsimple-0.2.3.dist-info/METADATA
fwsimple-0.2.3.dist-info/WHEEL
fwsimple-0.2.3.dist-info/entry_points.txt
fwsimple-0.2.3.dist-info/top_level.txt
fwsimple-0.2.3.dist-info/RECORD
