Metadata-Version: 2.1
Name: fwsimple
Version: 0.2.3
Summary: fwsimple
Home-page: UNKNOWN
Author: Rick Voormolen
Author-email: rick@voormolen.org
License: UNKNOWN
Platform: UNKNOWN
Requires-Dist: ipaddress
